videnc/__init__.py
videnc/__main__.py
videnc/video.py
videnc-0.0.3.post1.dist-info/LICENSE
videnc-0.0.3.post1.dist-info/METADATA
videnc-0.0.3.post1.dist-info/WHEEL
videnc-0.0.3.post1.dist-info/top_level.txt
videnc-0.0.3.post1.dist-info/RECORD
