Metadata-Version: 2.1
Name: videnc
Version: 0.0.3.post1
Summary: A FFMpeg wrapper written in python.
Home-page: https://github.com/awkawb/videnc
Author: Andrew Bryant
Author-email: abryant288@gmail.com
License: UNKNOWN
Platform: UNKNOWN
Classifier: Programming Language :: Python :: 3
Classifier: License :: OSI Approved :: MIT License
Classifier: Operating System :: OS Independent
Requires-Dist: av (<=6.2.0)
Requires-Dist: ffpb
Requires-Dist: python-find
